BuildBinary.py
PythonProjectBootstrapperTest/EntryPoint.py
PythonProjectBootstrapperTest/Math.py
PythonProjectBootstrapperTest/__init__.py
PythonProjectBootstrapperTest-0.1.3.dist-info/LICENSE.txt
PythonProjectBootstrapperTest-0.1.3.dist-info/METADATA
PythonProjectBootstrapperTest-0.1.3.dist-info/WHEEL
PythonProjectBootstrapperTest-0.1.3.dist-info/entry_points.txt
PythonProjectBootstrapperTest-0.1.3.dist-info/top_level.txt
PythonProjectBootstrapperTest-0.1.3.dist-info/RECORD
